bindecoder/__init__.py
bindecoder/avi.py
bindecoder/decoder.py
bindecoder/flv.py
bindecoder/hexdumper.py
bindecoder/jpg.py
bindecoder/mkv.py
bindecoder/qt.py
bindecoder/viewer.py
bindecoder_colinhogben-0.1.dist-info/LICENSE
bindecoder_colinhogben-0.1.dist-info/METADATA
bindecoder_colinhogben-0.1.dist-info/WHEEL
bindecoder_colinhogben-0.1.dist-info/top_level.txt
bindecoder_colinhogben-0.1.dist-info/RECORD
